sdg_eth/__init__.py
sdg_eth/pair.py
sdg_eth/tcpc.py
sdg_eth/tcps.py
sdg_eth/tmp.py
sdg_eth/udp_io.py
sdg_eth-1.0.dist-info/LICENSE
sdg_eth-1.0.dist-info/METADATA
sdg_eth-1.0.dist-info/WHEEL
sdg_eth-1.0.dist-info/top_level.txt
sdg_eth-1.0.dist-info/RECORD
