Metadata-Version: 2.1
Name: sdg-eth
Version: 1.0
Summary: udp_io, tcpc, tcps
Author: chernecov_ev
Author-email: chernecov.ev@gmail.com
Classifier: Programming Language :: Python :: 3
Classifier: License :: OSI Approved :: MIT License
Classifier: Operating System :: OS Independent
Requires-Python: >=3.4
License-File: LICENSE
